jupyterlab_browser_storage/__init__.py
jupyterlab_browser_storage/_version.py
jupyterlab_browser_storage-0.1.0.data/data/share/jupyter/labextensions/jupyterlab-browser-storage/package.json
jupyterlab_browser_storage-0.1.0.data/data/share/jupyter/labextensions/jupyterlab-browser-storage/schemas/jupyterlab-browser-storage/package.json.orig
jupyterlab_browser_storage-0.1.0.data/data/share/jupyter/labextensions/jupyterlab-browser-storage/schemas/jupyterlab-browser-storage/plugin.json
jupyterlab_browser_storage-0.1.0.data/data/share/jupyter/labextensions/jupyterlab-browser-storage/static/125.342c16af11a05d1a6fb2.js
jupyterlab_browser_storage-0.1.0.data/data/share/jupyter/labextensions/jupyterlab-browser-storage/static/616.f4ba30ad365064b3d3d1.js
jupyterlab_browser_storage-0.1.0.data/data/share/jupyter/labextensions/jupyterlab-browser-storage/static/728.c0e72b2686dab1dff7d4.js
jupyterlab_browser_storage-0.1.0.data/data/share/jupyter/labextensions/jupyterlab-browser-storage/static/790.b00f5c17183b52eb99dd.js
jupyterlab_browser_storage-0.1.0.data/data/share/jupyter/labextensions/jupyterlab-browser-storage/static/790.b00f5c17183b52eb99dd.js.LICENSE.txt
jupyterlab_browser_storage-0.1.0.data/data/share/jupyter/labextensions/jupyterlab-browser-storage/static/remoteEntry.289ef5005641db3c7231.js
jupyterlab_browser_storage-0.1.0.data/data/share/jupyter/labextensions/jupyterlab-browser-storage/static/style.js
jupyterlab_browser_storage-0.1.0.data/data/share/jupyter/labextensions/jupyterlab-browser-storage/static/third-party-licenses.json
jupyterlab_browser_storage-0.1.0.data/data/share/jupyter/labextensions/jupyterlab-browser-storage/install.json
jupyterlab_browser_storage-0.1.0.dist-info/METADATA
jupyterlab_browser_storage-0.1.0.dist-info/WHEEL
jupyterlab_browser_storage-0.1.0.dist-info/licenses/LICENSE
jupyterlab_browser_storage-0.1.0.dist-info/RECORD
